spherical_stats/__init__.py
spherical_stats/_acg.py
spherical_stats/_coordinate_systems.py
spherical_stats/_descriptive_stats.py
spherical_stats/_esag.py
spherical_stats/_plot_utils.py
spherical_stats/_utils.py
spherical_stats/_vmf.py
spherical_stats/_watson.py
spherical_stats/tasmanianData.csv
spherical_stats/test_vmf.py
spherical_stats-1.3.dist-info/LICENSE.txt
spherical_stats-1.3.dist-info/METADATA
spherical_stats-1.3.dist-info/WHEEL
spherical_stats-1.3.dist-info/top_level.txt
spherical_stats-1.3.dist-info/RECORD
