Metadata-Version: 2.1
Name: spherical-stats
Version: 1.3
Summary: Spherical statistics in Python
Home-page: https://github.com/dschmitz89/spherical_stats
Author: Daniel Schmitz
Author-email: danielschmitzsiegen@gmail.com
License: MIT
Platform: UNKNOWN
Requires-Dist: numpy
Requires-Dist: numba (>0.44)
Requires-Dist: scipy (>0.11)
